pythonai/__init__.py
pythonai/core.py
newpythonai-0.1.0.dist-info/METADATA
newpythonai-0.1.0.dist-info/WHEEL
newpythonai-0.1.0.dist-info/top_level.txt
newpythonai-0.1.0.dist-info/RECORD
